vax_receipts_cli/__init__.py
vax_receipts_cli/cli.py
vax_receipts_cli-0.1.1.dist-info/licenses/LICENSE
vax_receipts_cli-0.1.1.dist-info/METADATA
vax_receipts_cli-0.1.1.dist-info/WHEEL
vax_receipts_cli-0.1.1.dist-info/entry_points.txt
vax_receipts_cli-0.1.1.dist-info/top_level.txt
vax_receipts_cli-0.1.1.dist-info/RECORD
