Metadata-Version: 2.4
Name: vax-receipts-cli
Version: 0.1.1
Summary: Tiny CLI to list/open VibeAxis receipts (cornerstone posts & hubs).
Author: VibeAxis (Jason Bann)
License: MIT
Keywords: vibeaxis,ai,cli,tools,receipts
Classifier: Programming Language :: Python :: 3
Classifier: License :: OSI Approved :: MIT License
Classifier: Environment :: Console
Classifier: Topic :: Internet :: WWW/HTTP
Requires-Python: >=3.8
License-File: LICENSE
Dynamic: license-file
